{"cameraMode":{"drawMode":0,"name":"Shaded","section":"Shading Mode"},"sceneLighting":true,"audioPlay":false,"sceneViewState":{"showFog":true,"showMaterialUpdate":false,"showSkybox":true,"showFlares":true,"showImageEffects":true,"showParticleSystems":true},"in2DMode":false,"pivot":{"x":-4.881002426147461,"y":-21.469566345214845,"z":25.98256492614746},"rotation":{"x":0.4576437473297119,"y":-0.15926003456115724,"z":0.0837036520242691,"w":0.8707436323165894},"size":25.663772583007814,"orthographic":false}